README.rst
setup.py
autoslack/__init__.py
autoslack/autoslack.py
autoslack.egg-info/PKG-INFO
autoslack.egg-info/SOURCES.txt
autoslack.egg-info/dependency_links.txt
autoslack.egg-info/requires.txt
autoslack.egg-info/top_level.txt