Metadata-Version: 1.1
Name: autoslack
Version: 0.0.1.dev1
Summary: AutoSlack is a simple module designed to automate some tasks for http://slack.com.
Home-page: https://github.com/pythonjamaica/autoslack
Author: David Bain
Author-email: pigeonflight@gmail.com
License: MIT
Keywords: slack inviter automator
Platform: UNKNOWN
Classifier: Development Status :: 3 - Alpha
Classifier: Intended Audience :: Developers
Classifier: Topic :: Software Development :: Libraries
Classifier: License :: OSI Approved :: MIT License
Classifier: Programming Language :: Python :: 2
Classifier: Programming Language :: Python :: 2.6
Classifier: Programming Language :: Python :: 2.7
Classifier: Programming Language :: Python :: 3
Classifier: Programming Language :: Python :: 3.2
Classifier: Programming Language :: Python :: 3.3
Classifier: Programming Language :: Python :: 3.4
